py2rdf/__init__.py
py2rdf/rdf_model.py
py2rdf-0.1.2.dist-info/licenses/LICENSE
py2rdf-0.1.2.dist-info/METADATA
py2rdf-0.1.2.dist-info/WHEEL
py2rdf-0.1.2.dist-info/top_level.txt
py2rdf-0.1.2.dist-info/RECORD
