Metadata-Version: 2.4
Name: py2rdf
Version: 0.1.2
Summary: A Python library for mapping Python objects to RDF graphs using Pydantic and rdflib.
Author-email: An Lam <an.lam@sintef.no>
License-Expression: MIT
Project-URL: Homepage, https://github.com/SINTEF-9012/py2rdf
Project-URL: Issues, https://github.com/SINTEF-9012/py2rdf/issues
Classifier: Programming Language :: Python :: 3
Classifier: Operating System :: OS Independent
Requires-Python: >=3.9
License-File: LICENSE
Requires-Dist: rdflib>=7.0.0
Requires-Dist: pydantic>=2.9.2
Requires-Dist: typing-extensions>=4.12.0
Dynamic: license-file
